scythe/__init__.py
scythe/client.py
scythe/defaults.py
scythe/exceptions.py
scythe/request_resource.py
scythe/api_resources/__init__.py
scythe/api_resources/abstract.py
scythe/api_resources/domain.py
scythe/api_resources/event_type.py
scythe/api_resources/subscriber.py
scythe/api_resources/subscriber_event_type.py
scythe/api_resources/subscriber_url.py
scythe_python-1.1.1.dist-info/LICENSE
scythe_python-1.1.1.dist-info/METADATA
scythe_python-1.1.1.dist-info/WHEEL
scythe_python-1.1.1.dist-info/top_level.txt
scythe_python-1.1.1.dist-info/zip-safe
scythe_python-1.1.1.dist-info/RECORD
