Metadata-Version: 2.1
Name: scythe-python
Version: 1.1.1
Summary: Python SDK for Scythe
Home-page: https://github.com/yat-co/scythe-python
Author: YAT, LLC
Author-email: rgoss@yat.ai
License: MIT
Classifier: Intended Audience :: Developers
Classifier: Programming Language :: Python
Classifier: Programming Language :: Python :: 3
Classifier: Programming Language :: Python :: 3.6
Classifier: Programming Language :: Python :: 3.8
Classifier: Programming Language :: Python :: 3.9
License-File: LICENSE
Requires-Dist: requests
